[{"title":"Congé test test","start":"2019-04-29T08:00:00.0000000Z","end":"2019-04-29T17:00:00.0000000Z","color":"green","textColor":"white"},{"title":"Congé Mzoughui Houda","start":"2019-05-03T12:00:00.0000000Z","end":"2019-05-03T17:00:00.0000000Z","color":"green","textColor":"white"},{"title":"Congé Mzoughui Houda","start":"2019-05-10T10:00:00.0000000Z","end":"2019-05-10T14:00:00.0000000Z","color":"green","textColor":"white"},{"title":"Congé Mzoughi Mohamed","start":"1919-05-18T05:00:00.0000000Z","end":"2019-05-19T17:00:00.0000000Z","color":"green","textColor":"white"},{"title":"Congé Mzoughui Houda","start":"2019-05-31T10:30:00.0000000Z","end":"2019-05-31T14:00:00.0000000Z","color":"green","textColor":"white"},{"title":"Autorisation Mzoughui Houda","start":"2019-05-03T10:30:00.0000000Z","end":"2019-05-03T12:00:00.0000000Z","color":"blue","textColor":"white"}]